{
  "players": [
    {
      "id": "191614",
      "name": "Fred",
      "position": "CM",
      "rating": 75,
      "value": 0,
      "image": "https://img.a.transfermarkt.technology/portrait/header/191614-1728391871.JPG",
      "club": "Fenerbahce"
    },
    {
      "id": "283223",
      "name": "Emre Mor",
      "position": "RW",
      "rating": 75,
      "value": 0,
      "image": "https://img.a.transfermarkt.technology/portrait/header/283223-1712157441.png",
      "club": "Fenerbahce"
    },
    {
      "id": "1194135",
      "name": "Ata Gür",
      "position": "CDM",
      "rating": 75,
      "value": 0,
      "image": "https://img.a.transfermarkt.technology/portrait/header/1194135-1705136199.png",
      "club": "Fenerbahce U19"
    },
    {
      "id": "382528",
      "name": "Kerem Aktürkoğlu",
      "position": "LW",
      "rating": 75,
      "value": 0,
      "image": "https://b.fssta.com/uploads/application/soccer/headshots/39894.vresize.350.350.medium.1.png",
      "club": "Fenerbahce"
    },
    {
      "id": "320748",
      "name": "Sebastian Szymański",
      "position": "CAM",
      "rating": 75,
      "value": 0,
      "image": "https://img.a.transfermarkt.technology/portrait/header/320748-1728392667.JPG",
      "club": "Fenerbahce"
    },
    {
      "id": "671591",
      "name": "Dorgeles Nene",
      "position": "RW",
      "rating": 75,
      "value": 0,
      "image": "https://img.a.transfermarkt.technology/portrait/header/671591-1754993214.png",
      "club": "Fenerbahce"
    },
    {
      "id": "388820",
      "name": "Levent Mercan",
      "position": "LB",
      "rating": 75,
      "value": 0,
      "image": "https://img.a.transfermarkt.technology/portrait/header/388820-1695219229.png",
      "club": "Fenerbahce"
    },
    {
      "id": "231572",
      "name": "Nélson Semedo",
      "position": "RB",
      "rating": 75,
      "value": 0,
      "image": "https://img.a.transfermarkt.technology/portrait/header/231572-1684487147.jpg",
      "club": "Fenerbahce"
    },
    {
      "id": "655895",
      "name": "Bartuğ Elmaz",
      "position": "CDM",
      "rating": 75,
      "value": 0,
      "image": "https://img.a.transfermarkt.technology/portrait/header/655895-1728392470.JPG",
      "club": "Fenerbahce"
    },
    {
      "id": "216603",
      "name": "İrfan Can Kahveci",
      "position": "RW",
      "rating": 75,
      "value": 0,
      "image": "https://img.a.transfermarkt.technology/portrait/header/216603-1728391961.JPG",
      "club": "Fenerbahce"
    },
    {
      "id": "296622",
      "name": "Marco Asensio",
      "position": "CAM",
      "rating": 75,
      "value": 0,
      "image": "https://img.a.transfermarkt.technology/portrait/header/296622-1752151998.jpg",
      "club": "Fenerbahce"
    },
    {
      "id": "45671",
      "name": "Cenk Tosun",
      "position": "ST",
      "rating": 75,
      "value": 0,
      "image": "https://img.a.transfermarkt.technology/portrait/header/45671-1728392200.JPG",
      "club": "Fenerbahce"
    },
    {
      "id": "613725",
      "name": "İsmail Yüksek",
      "position": "CDM",
      "rating": 75,
      "value": 0,
      "image": "https://img.a.transfermarkt.technology/portrait/header/613725-1728391640.JPG",
      "club": "Fenerbahce"
    },
    {
      "id": "353922",
      "name": "Mert Müldür",
      "position": "RB",
      "rating": 75,
      "value": 0,
      "image": "https://img.a.transfermarkt.technology/portrait/header/353922-1728391929.JPG",
      "club": "Fenerbahce"
    },
    {
      "id": "649317",
      "name": "Jhon Durán",
      "position": "ST",
      "rating": 75,
      "value": 0,
      "image": "https://img.a.transfermarkt.technology/portrait/header/649317-1753257202.jpg",
      "club": "Fenerbahce"
    },
    {
      "id": "204069",
      "name": "Milan Škriniar",
      "position": "CB",
      "rating": 75,
      "value": 0,
      "image": "https://img.a.transfermarkt.technology/portrait/header/204069-1738665259.png",
      "club": "Fenerbahce"
    },
    {
      "id": "238223",
      "name": "Ederson",
      "position": "GK",
      "rating": 75,
      "value": 0,
      "image": "https://img.a.transfermarkt.technology/portrait/header/238223-1713391842.jpg",
      "club": "Fenerbahce"
    },
    {
      "id": "433049",
      "name": "Youssef En-Nesyri",
      "position": "ST",
      "rating": 75,
      "value": 0,
      "image": "https://img.a.transfermarkt.technology/portrait/header/433049-1728392433.JPG",
      "club": "Fenerbahce"
    },
    {
      "id": "258626",
      "name": "Talisca",
      "position": "CAM",
      "rating": 75,
      "value": 0,
      "image": "https://img.a.transfermarkt.technology/portrait/header/258626-1738664288.jpg",
      "club": "Fenerbahce"
    },
    {
      "id": "401356",
      "name": "Edson Álvarez",
      "position": "CDM",
      "rating": 75,
      "value": 0,
      "image": "https://img.a.transfermarkt.technology/portrait/header/401356-1742822886.jpg",
      "club": "Fenerbahce"
    },
    {
      "id": "581329",
      "name": "Archie Brown",
      "position": "LB",
      "rating": 75,
      "value": 0,
      "image": "https://img.a.transfermarkt.technology/portrait/header/581329-1691840592.jpg",
      "club": "Fenerbahce"
    },
    {
      "id": "286170",
      "name": "Tarık Çetin",
      "position": "GK",
      "rating": 75,
      "value": 0,
      "image": "https://img.a.transfermarkt.technology/portrait/header/286170-1752478061.jpg",
      "club": "Fenerbahce"
    },
    {
      "id": "322873",
      "name": "İrfan Can Eğribayat",
      "position": "GK",
      "rating": 75,
      "value": 0,
      "image": "https://img.a.transfermarkt.technology/portrait/header/322873-1728392495.JPG",
      "club": "Fenerbahce"
    },
    {
      "id": "889136",
      "name": "Yiğit Efe Demir",
      "position": "CB",
      "rating": 75,
      "value": 0,
      "image": "https://img.a.transfermarkt.technology/portrait/header/889136-1750150628.jpg",
      "club": "Fenerbahce"
    },
    {
      "id": "591361",
      "name": "Jayden Oosterwolde",
      "position": "LB",
      "rating": 75,
      "value": 0,
      "image": "https://img.a.transfermarkt.technology/portrait/big/591361-1728392223.JPG?lm=1",
      "club": "Fenerbahce"
    },
    {
      "id": "320141",
      "name": "Çağlar Söyüncü",
      "position": "CB",
      "rating": 75,
      "value": 0,
      "image": "https://img.a.transfermarkt.technology/portrait/header/320141-1728391611.JPG?lm=1",
      "club": "Fenerbahce"
    },
    {
      "id": "563749",
      "name": "Oğuz Aydın",
      "position": "LW",
      "rating": 75,
      "value": 0,
      "image": "https://img.a.transfermarkt.technology/portrait/big/563749-1728392736.JPG?lm=1",
      "club": "Fenerbahce"
    },
    {
      "id": "410158",
      "name": "Rodrigo Becão",
      "position": "CB",
      "rating": 75,
      "value": 0,
      "image": "https://img.a.transfermarkt.technology/portrait/big/410158-1728392628.JPG?lm=1",
      "club": "Fenerbahce"
    }
  ]
}